noselfs/__init__.py
noselfs/decorator.py
noselfs/meta.py
noselfs/testbase.py
noselfs-0.0.11.dist-info/DESCRIPTION.rst
noselfs-0.0.11.dist-info/METADATA
noselfs-0.0.11.dist-info/RECORD
noselfs-0.0.11.dist-info/WHEEL
noselfs-0.0.11.dist-info/metadata.json
noselfs-0.0.11.dist-info/top_level.txt
