Metadata-Version: 2.0
Name: noselfs
Version: 0.0.11
Summary: A nosetest add-on that gets lfs files
Home-page: https://github.com/grantstephens/noselfs
Author: Grant Stephens
Author-email: grant@stephens.co.za
License: MIT
Download-URL: https://github.com/grantstephens/noselfs/tarball/0.0.11
Keywords: nose test lfs
Platform: UNKNOWN
Classifier: Development Status :: 4 - Beta
Classifier: Intended Audience :: Developers
Classifier: License :: OSI Approved :: MIT License
Classifier: Topic :: Software Development :: Testing
Classifier: Programming Language :: Python :: 2
Classifier: Programming Language :: Python :: 2.6
Classifier: Programming Language :: Python :: 2.7
Classifier: Programming Language :: Python :: 3
Classifier: Programming Language :: Python :: 3.2
Classifier: Programming Language :: Python :: 3.3
Classifier: Programming Language :: Python :: 3.4
Classifier: Programming Language :: Python :: 3.5
Classifier: Programming Language :: Python :: 3.6
Requires-Dist: nose
Provides-Extra: test
Requires-Dist: nose; extra == 'test'
Requires-Dist: requests-mock (>=0.7.0); extra == 'test'
